sample/__init__.py
sample/core.py
sample/helpers.py
scrapy_statsd_middleware/__init__.py
scrapy_statsd_middleware/statsd_middleware.py
scrapy_statsd_middleware-0.0.8.dist-info/DESCRIPTION.rst
scrapy_statsd_middleware-0.0.8.dist-info/METADATA
scrapy_statsd_middleware-0.0.8.dist-info/metadata.json
scrapy_statsd_middleware-0.0.8.dist-info/RECORD
scrapy_statsd_middleware-0.0.8.dist-info/top_level.txt
scrapy_statsd_middleware-0.0.8.dist-info/WHEEL
