Metadata-Version: 2.0
Name: scrapy-statsd-middleware
Version: 0.0.8
Summary: Statsd integration middleware for scrapy
Home-page: https://github.com/zachgoldstein/scrapy-statsd
Author: Zach Goldstein
Author-email: zachgold@gmail.com
License: Apache 2.0
Platform: UNKNOWN
Requires-Dist: Scrapy (>=1.0.5)
Requires-Dist: statsd (==3.2.1)
Provides-Extra: test
Requires-Dist: mock (==2.0.0); extra == 'test'
